{
  "items": [
    {
      "login": "bradfitz",
      "id": 2621,
      "avatarUrl": "https://avatars2.githubusercontent.com/u/2621?v=3",
      "gravatarId": "",
      "url": "https://api.github.com/users/bradfitz",
      "htmlUrl": "https://github.com/bradfitz",
      "followersUrl": "https://api.github.com/users/bradfitz/followers",
      "subscriptionsUrl": "https://api.github.com/users/bradfitz/subscriptions",
      "organizationsUrl": "https://api.github.com/users/bradfitz/orgs",
      "reposUrl": "https://api.github.com/users/bradfitz/repos",
      "receivedEventsUrl": "https://api.github.com/users/bradfitz/received_events",
      "type": "User",
      "contributions": 197
    },
    {
      "login": "adg",
      "id": 8446613,
      "avatarUrl": "https://avatars3.githubusercontent.com/u/8446613?v=3",
      "gravatarId": "",
      "url": "https://api.github.com/users/adg",
      "htmlUrl": "https://github.com/adg",
      "followersUrl": "https://api.github.com/users/adg/followers",
      "subscriptionsUrl": "https://api.github.com/users/adg/subscriptions",
      "organizationsUrl": "https://api.github.com/users/adg/orgs",
      "reposUrl": "https://api.github.com/users/adg/repos",
      "receivedEventsUrl": "https://api.github.com/users/adg/received_events",
      "type": "User",
      "contributions": 156
    },
    {
      "login": "paranoiacblack",
      "id": 1035296,
      "avatarUrl": "https://avatars0.githubusercontent.com/u/1035296?v=3",
      "gravatarId": "",
      "url": "https://api.github.com/users/paranoiacblack",
      "htmlUrl": "https://github.com/paranoiacblack",
      "followersUrl": "https://api.github.com/users/paranoiacblack/followers",
      "subscriptionsUrl": "https://api.github.com/users/paranoiacblack/subscriptions",
      "organizationsUrl": "https://api.github.com/users/paranoiacblack/orgs",
      "reposUrl": "https://api.github.com/users/paranoiacblack/repos",
      "receivedEventsUrl": "https://api.github.com/users/paranoiacblack/received_events",
      "type": "User",
      "contributions": 36
    },
    {
      "login": "dvyukov",
      "id": 1095328,
      "avatarUrl": "https://avatars0.githubusercontent.com/u/1095328?v=3",
      "gravatarId": "",
      "url": "https://api.github.com/users/dvyukov",
      "htmlUrl": "https://github.com/dvyukov",
      "followersUrl": "https://api.github.com/users/dvyukov/followers",
      "subscriptionsUrl": "https://api.github.com/users/dvyukov/subscriptions",
      "organizationsUrl": "https://api.github.com/users/dvyukov/orgs",
      "reposUrl": "https://api.github.com/users/dvyukov/repos",
      "receivedEventsUrl": "https://api.github.com/users/dvyukov/received_events",
      "type": "User",
      "contributions": 32
    },
    {
      "login": "crawshaw",
      "id": 161319,
      "avatarUrl": "https://avatars3.githubusercontent.com/u/161319?v=3",
      "gravatarId": "",
      "url": "https://api.github.com/users/crawshaw",
      "htmlUrl": "https://github.com/crawshaw",
      "followersUrl": "https://api.github.com/users/crawshaw/followers",
      "subscriptionsUrl": "https://api.github.com/users/crawshaw/subscriptions",
      "organizationsUrl": "https://api.github.com/users/crawshaw/orgs",
      "reposUrl": "https://api.github.com/users/crawshaw/repos",
      "receivedEventsUrl": "https://api.github.com/users/crawshaw/received_events",
      "type": "User",
      "contributions": 29
    },
    {
      "login": "evandbrown",
      "id": 656941,
      "avatarUrl": "https://avatars2.githubusercontent.com/u/656941?v=3",
      "gravatarId": "",
      "url": "https://api.github.com/users/evandbrown",
      "htmlUrl": "https://github.com/evandbrown",
      "followersUrl": "https://api.github.com/users/evandbrown/followers",
      "subscriptionsUrl": "https://api.github.com/users/evandbrown/subscriptions",
      "organizationsUrl": "https://api.github.com/users/evandbrown/orgs",
      "reposUrl": "https://api.github.com/users/evandbrown/repos",
      "receivedEventsUrl": "https://api.github.com/users/evandbrown/received_events",
      "type": "User",
      "contributions": 12
    },
    {
      "login": "0intro",
      "id": 6043744,
      "avatarUrl": "https://avatars0.githubusercontent.com/u/6043744?v=3",
      "gravatarId": "",
      "url": "https://api.github.com/users/0intro",
      "htmlUrl": "https://github.com/0intro",
      "followersUrl": "https://api.github.com/users/0intro/followers",
      "subscriptionsUrl": "https://api.github.com/users/0intro/subscriptions",
      "organizationsUrl": "https://api.github.com/users/0intro/orgs",
      "reposUrl": "https://api.github.com/users/0intro/repos",
      "receivedEventsUrl": "https://api.github.com/users/0intro/received_events",
      "type": "User",
      "contributions": 9
    },
    {
      "login": "aclements",
      "id": 2688315,
      "avatarUrl": "https://avatars3.githubusercontent.com/u/2688315?v=3",
      "gravatarId": "",
      "url": "https://api.github.com/users/aclements",
      "htmlUrl": "https://github.com/aclements",
      "followersUrl": "https://api.github.com/users/aclements/followers",
      "subscriptionsUrl": "https://api.github.com/users/aclements/subscriptions",
      "organizationsUrl": "https://api.github.com/users/aclements/orgs",
      "reposUrl": "https://api.github.com/users/aclements/repos",
      "receivedEventsUrl": "https://api.github.com/users/aclements/received_events",
      "type": "User",
      "contributions": 7
    },
    {
      "login": "alexbrainman",
      "id": 9796621,
      "avatarUrl": "https://avatars1.githubusercontent.com/u/9796621?v=3",
      "gravatarId": "",
      "url": "https://api.github.com/users/alexbrainman",
      "htmlUrl": "https://github.com/alexbrainman",
      "followersUrl": "https://api.github.com/users/alexbrainman/followers",
      "subscriptionsUrl": "https://api.github.com/users/alexbrainman/subscriptions",
      "organizationsUrl": "https://api.github.com/users/alexbrainman/orgs",
      "reposUrl": "https://api.github.com/users/alexbrainman/repos",
      "receivedEventsUrl": "https://api.github.com/users/alexbrainman/received_events",
      "type": "User",
      "contributions": 6
    },
    {
      "login": "davecheney",
      "id": 7171,
      "avatarUrl": "https://avatars3.githubusercontent.com/u/7171?v=3",
      "gravatarId": "",
      "url": "https://api.github.com/users/davecheney",
      "htmlUrl": "https://github.com/davecheney",
      "followersUrl": "https://api.github.com/users/davecheney/followers",
      "subscriptionsUrl": "https://api.github.com/users/davecheney/subscriptions",
      "organizationsUrl": "https://api.github.com/users/davecheney/orgs",
      "reposUrl": "https://api.github.com/users/davecheney/repos",
      "receivedEventsUrl": "https://api.github.com/users/davecheney/received_events",
      "type": "User",
      "contributions": 6
    },
    {
      "login": "rsc",
      "id": 104030,
      "avatarUrl": "https://avatars2.githubusercontent.com/u/104030?v=3",
      "gravatarId": "",
      "url": "https://api.github.com/users/rsc",
      "htmlUrl": "https://github.com/rsc",
      "followersUrl": "https://api.github.com/users/rsc/followers",
      "subscriptionsUrl": "https://api.github.com/users/rsc/subscriptions",
      "organizationsUrl": "https://api.github.com/users/rsc/orgs",
      "reposUrl": "https://api.github.com/users/rsc/repos",
      "receivedEventsUrl": "https://api.github.com/users/rsc/received_events",
      "type": "User",
      "contributions": 6
    },
    {
      "login": "saljam",
      "id": 751023,
      "avatarUrl": "https://avatars3.githubusercontent.com/u/751023?v=3",
      "gravatarId": "",
      "url": "https://api.github.com/users/saljam",
      "htmlUrl": "https://github.com/saljam",
      "followersUrl": "https://api.github.com/users/saljam/followers",
      "subscriptionsUrl": "https://api.github.com/users/saljam/subscriptions",
      "organizationsUrl": "https://api.github.com/users/saljam/orgs",
      "reposUrl": "https://api.github.com/users/saljam/repos",
      "receivedEventsUrl": "https://api.github.com/users/saljam/received_events",
      "type": "User",
      "contributions": 6
    },
    {
      "login": "minux",
      "id": 135652,
      "avatarUrl": "https://avatars2.githubusercontent.com/u/135652?v=3",
      "gravatarId": "",
      "url": "https://api.github.com/users/minux",
      "htmlUrl": "https://github.com/minux",
      "followersUrl": "https://api.github.com/users/minux/followers",
      "subscriptionsUrl": "https://api.github.com/users/minux/subscriptions",
      "organizationsUrl": "https://api.github.com/users/minux/orgs",
      "reposUrl": "https://api.github.com/users/minux/repos",
      "receivedEventsUrl": "https://api.github.com/users/minux/received_events",
      "type": "User",
      "contributions": 6
    },
    {
      "login": "proppy",
      "id": 5268,
      "avatarUrl": "https://avatars3.githubusercontent.com/u/5268?v=3",
      "gravatarId": "",
      "url": "https://api.github.com/users/proppy",
      "htmlUrl": "https://github.com/proppy",
      "followersUrl": "https://api.github.com/users/proppy/followers",
      "subscriptionsUrl": "https://api.github.com/users/proppy/subscriptions",
      "organizationsUrl": "https://api.github.com/users/proppy/orgs",
      "reposUrl": "https://api.github.com/users/proppy/repos",
      "receivedEventsUrl": "https://api.github.com/users/proppy/received_events",
      "type": "User",
      "contributions": 3
    },
    {
      "login": "wathiede",
      "id": 1043363,
      "avatarUrl": "https://avatars3.githubusercontent.com/u/1043363?v=3",
      "gravatarId": "",
      "url": "https://api.github.com/users/wathiede",
      "htmlUrl": "https://github.com/wathiede",
      "followersUrl": "https://api.github.com/users/wathiede/followers",
      "subscriptionsUrl": "https://api.github.com/users/wathiede/subscriptions",
      "organizationsUrl": "https://api.github.com/users/wathiede/orgs",
      "reposUrl": "https://api.github.com/users/wathiede/repos",
      "receivedEventsUrl": "https://api.github.com/users/wathiede/received_events",
      "type": "User",
      "contributions": 2
    },
    {
      "login": "ceh",
      "id": 248952,
      "avatarUrl": "https://avatars0.githubusercontent.com/u/248952?v=3",
      "gravatarId": "",
      "url": "https://api.github.com/users/ceh",
      "htmlUrl": "https://github.com/ceh",
      "followersUrl": "https://api.github.com/users/ceh/followers",
      "subscriptionsUrl": "https://api.github.com/users/ceh/subscriptions",
      "organizationsUrl": "https://api.github.com/users/ceh/orgs",
      "reposUrl": "https://api.github.com/users/ceh/repos",
      "receivedEventsUrl": "https://api.github.com/users/ceh/received_events",
      "type": "User",
      "contributions": 2
    },
    {
      "login": "RichardLitt",
      "id": 910753,
      "avatarUrl": "https://avatars0.githubusercontent.com/u/910753?v=3",
      "gravatarId": "",
      "url": "https://api.github.com/users/RichardLitt",
      "htmlUrl": "https://github.com/RichardLitt",
      "followersUrl": "https://api.github.com/users/RichardLitt/followers",
      "subscriptionsUrl": "https://api.github.com/users/RichardLitt/subscriptions",
      "organizationsUrl": "https://api.github.com/users/RichardLitt/orgs",
      "reposUrl": "https://api.github.com/users/RichardLitt/repos",
      "receivedEventsUrl": "https://api.github.com/users/RichardLitt/received_events",
      "type": "User",
      "contributions": 2
    },
    {
      "login": "4ad",
      "id": 1331747,
      "avatarUrl": "https://avatars0.githubusercontent.com/u/1331747?v=3",
      "gravatarId": "",
      "url": "https://api.github.com/users/4ad",
      "htmlUrl": "https://github.com/4ad",
      "followersUrl": "https://api.github.com/users/4ad/followers",
      "subscriptionsUrl": "https://api.github.com/users/4ad/subscriptions",
      "organizationsUrl": "https://api.github.com/users/4ad/orgs",
      "reposUrl": "https://api.github.com/users/4ad/repos",
      "receivedEventsUrl": "https://api.github.com/users/4ad/received_events",
      "type": "User",
      "contributions": 1
    },
    {
      "login": "kardianos",
      "id": 755121,
      "avatarUrl": "https://avatars1.githubusercontent.com/u/755121?v=3",
      "gravatarId": "",
      "url": "https://api.github.com/users/kardianos",
      "htmlUrl": "https://github.com/kardianos",
      "followersUrl": "https://api.github.com/users/kardianos/followers",
      "subscriptionsUrl": "https://api.github.com/users/kardianos/subscriptions",
      "organizationsUrl": "https://api.github.com/users/kardianos/orgs",
      "reposUrl": "https://api.github.com/users/kardianos/repos",
      "receivedEventsUrl": "https://api.github.com/users/kardianos/received_events",
      "type": "User",
      "contributions": 1
    },
    {
      "login": "dsymonds",
      "id": 31506,
      "avatarUrl": "https://avatars1.githubusercontent.com/u/31506?v=3",
      "gravatarId": "",
      "url": "https://api.github.com/users/dsymonds",
      "htmlUrl": "https://github.com/dsymonds",
      "followersUrl": "https://api.github.com/users/dsymonds/followers",
      "subscriptionsUrl": "https://api.github.com/users/dsymonds/subscriptions",
      "organizationsUrl": "https://api.github.com/users/dsymonds/orgs",
      "reposUrl": "https://api.github.com/users/dsymonds/repos",
      "receivedEventsUrl": "https://api.github.com/users/dsymonds/received_events",
      "type": "User",
      "contributions": 1
    },
    {
      "login": "hyangah",
      "id": 4999471,
      "avatarUrl": "https://avatars3.githubusercontent.com/u/4999471?v=3",
      "gravatarId": "",
      "url": "https://api.github.com/users/hyangah",
      "htmlUrl": "https://github.com/hyangah",
      "followersUrl": "https://api.github.com/users/hyangah/followers",
      "subscriptionsUrl": "https://api.github.com/users/hyangah/subscriptions",
      "organizationsUrl": "https://api.github.com/users/hyangah/orgs",
      "reposUrl": "https://api.github.com/users/hyangah/repos",
      "receivedEventsUrl": "https://api.github.com/users/hyangah/received_events",
      "type": "User",
      "contributions": 1
    },
    {
      "login": "josharian",
      "id": 67496,
      "avatarUrl": "https://avatars1.githubusercontent.com/u/67496?v=3",
      "gravatarId": "",
      "url": "https://api.github.com/users/josharian",
      "htmlUrl": "https://github.com/josharian",
      "followersUrl": "https://api.github.com/users/josharian/followers",
      "subscriptionsUrl": "https://api.github.com/users/josharian/subscriptions",
      "organizationsUrl": "https://api.github.com/users/josharian/orgs",
      "reposUrl": "https://api.github.com/users/josharian/repos",
      "receivedEventsUrl": "https://api.github.com/users/josharian/received_events",
      "type": "User",
      "contributions": 1
    },
    {
      "login": "Luit",
      "id": 388247,
      "avatarUrl": "https://avatars1.githubusercontent.com/u/388247?v=3",
      "gravatarId": "",
      "url": "https://api.github.com/users/Luit",
      "htmlUrl": "https://github.com/Luit",
      "followersUrl": "https://api.github.com/users/Luit/followers",
      "subscriptionsUrl": "https://api.github.com/users/Luit/subscriptions",
      "organizationsUrl": "https://api.github.com/users/Luit/orgs",
      "reposUrl": "https://api.github.com/users/Luit/repos",
      "receivedEventsUrl": "https://api.github.com/users/Luit/received_events",
      "type": "User",
      "contributions": 1
    },
    {
      "login": "MDrollette",
      "id": 329784,
      "avatarUrl": "https://avatars1.githubusercontent.com/u/329784?v=3",
      "gravatarId": "",
      "url": "https://api.github.com/users/MDrollette",
      "htmlUrl": "https://github.com/MDrollette",
      "followersUrl": "https://api.github.com/users/MDrollette/followers",
      "subscriptionsUrl": "https://api.github.com/users/MDrollette/subscriptions",
      "organizationsUrl": "https://api.github.com/users/MDrollette/orgs",
      "reposUrl": "https://api.github.com/users/MDrollette/repos",
      "receivedEventsUrl": "https://api.github.com/users/MDrollette/received_events",
      "type": "User",
      "contributions": 1
    },
    {
      "login": "mdempsky",
      "id": 38349,
      "avatarUrl": "https://avatars3.githubusercontent.com/u/38349?v=3",
      "gravatarId": "",
      "url": "https://api.github.com/users/mdempsky",
      "htmlUrl": "https://github.com/mdempsky",
      "followersUrl": "https://api.github.com/users/mdempsky/followers",
      "subscriptionsUrl": "https://api.github.com/users/mdempsky/subscriptions",
      "organizationsUrl": "https://api.github.com/users/mdempsky/orgs",
      "reposUrl": "https://api.github.com/users/mdempsky/repos",
      "receivedEventsUrl": "https://api.github.com/users/mdempsky/received_events",
      "type": "User",
      "contributions": 1
    },
    {
      "login": "mikioh",
      "id": 92117,
      "avatarUrl": "https://avatars2.githubusercontent.com/u/92117?v=3",
      "gravatarId": "",
      "url": "https://api.github.com/users/mikioh",
      "htmlUrl": "https://github.com/mikioh",
      "followersUrl": "https://api.github.com/users/mikioh/followers",
      "subscriptionsUrl": "https://api.github.com/users/mikioh/subscriptions",
      "organizationsUrl": "https://api.github.com/users/mikioh/orgs",
      "reposUrl": "https://api.github.com/users/mikioh/repos",
      "receivedEventsUrl": "https://api.github.com/users/mikioh/received_events",
      "type": "User",
      "contributions": 1
    },
    {
      "login": "robpike",
      "id": 4324516,
      "avatarUrl": "https://avatars3.githubusercontent.com/u/4324516?v=3",
      "gravatarId": "",
      "url": "https://api.github.com/users/robpike",
      "htmlUrl": "https://github.com/robpike",
      "followersUrl": "https://api.github.com/users/robpike/followers",
      "subscriptionsUrl": "https://api.github.com/users/robpike/subscriptions",
      "organizationsUrl": "https://api.github.com/users/robpike/orgs",
      "reposUrl": "https://api.github.com/users/robpike/repos",
      "receivedEventsUrl": "https://api.github.com/users/robpike/received_events",
      "type": "User",
      "contributions": 1
    },
    {
      "login": "griesemer",
      "id": 8528975,
      "avatarUrl": "https://avatars1.githubusercontent.com/u/8528975?v=3",
      "gravatarId": "",
      "url": "https://api.github.com/users/griesemer",
      "htmlUrl": "https://github.com/griesemer",
      "followersUrl": "https://api.github.com/users/griesemer/followers",
      "subscriptionsUrl": "https://api.github.com/users/griesemer/subscriptions",
      "organizationsUrl": "https://api.github.com/users/griesemer/orgs",
      "reposUrl": "https://api.github.com/users/griesemer/repos",
      "receivedEventsUrl": "https://api.github.com/users/griesemer/received_events",
      "type": "User",
      "contributions": 1
    }
  ],
  "url": "/repos/ipfs/golang-build/contributors"
}