{
  "items": [
    {
      "login": "jbenet",
      "id": 138401,
      "avatarUrl": "https://avatars.githubusercontent.com/u/138401?v=3",
      "gravatarId": "",
      "url": "https://api.github.com/users/jbenet",
      "htmlUrl": "https://github.com/jbenet",
      "followersUrl": "https://api.github.com/users/jbenet/followers",
      "subscriptionsUrl": "https://api.github.com/users/jbenet/subscriptions",
      "organizationsUrl": "https://api.github.com/users/jbenet/orgs",
      "reposUrl": "https://api.github.com/users/jbenet/repos",
      "receivedEventsUrl": "https://api.github.com/users/jbenet/received_events",
      "type": "User",
      "contributions": 102
    },
    {
      "login": "RichardLitt",
      "id": 910753,
      "avatarUrl": "https://avatars.githubusercontent.com/u/910753?v=3",
      "gravatarId": "",
      "url": "https://api.github.com/users/RichardLitt",
      "htmlUrl": "https://github.com/RichardLitt",
      "followersUrl": "https://api.github.com/users/RichardLitt/followers",
      "subscriptionsUrl": "https://api.github.com/users/RichardLitt/subscriptions",
      "organizationsUrl": "https://api.github.com/users/RichardLitt/orgs",
      "reposUrl": "https://api.github.com/users/RichardLitt/repos",
      "receivedEventsUrl": "https://api.github.com/users/RichardLitt/received_events",
      "type": "User",
      "contributions": 51
    },
    {
      "login": "dylanPowers",
      "id": 1594851,
      "avatarUrl": "https://avatars.githubusercontent.com/u/1594851?v=3",
      "gravatarId": "",
      "url": "https://api.github.com/users/dylanPowers",
      "htmlUrl": "https://github.com/dylanPowers",
      "followersUrl": "https://api.github.com/users/dylanPowers/followers",
      "subscriptionsUrl": "https://api.github.com/users/dylanPowers/subscriptions",
      "organizationsUrl": "https://api.github.com/users/dylanPowers/orgs",
      "reposUrl": "https://api.github.com/users/dylanPowers/repos",
      "receivedEventsUrl": "https://api.github.com/users/dylanPowers/received_events",
      "type": "User",
      "contributions": 9
    },
    {
      "login": "whyrusleeping",
      "id": 1243164,
      "avatarUrl": "https://avatars.githubusercontent.com/u/1243164?v=3",
      "gravatarId": "",
      "url": "https://api.github.com/users/whyrusleeping",
      "htmlUrl": "https://github.com/whyrusleeping",
      "followersUrl": "https://api.github.com/users/whyrusleeping/followers",
      "subscriptionsUrl": "https://api.github.com/users/whyrusleeping/subscriptions",
      "organizationsUrl": "https://api.github.com/users/whyrusleeping/orgs",
      "reposUrl": "https://api.github.com/users/whyrusleeping/repos",
      "receivedEventsUrl": "https://api.github.com/users/whyrusleeping/received_events",
      "type": "User",
      "contributions": 7
    },
    {
      "login": "ali01",
      "id": 184424,
      "avatarUrl": "https://avatars.githubusercontent.com/u/184424?v=3",
      "gravatarId": "",
      "url": "https://api.github.com/users/ali01",
      "htmlUrl": "https://github.com/ali01",
      "followersUrl": "https://api.github.com/users/ali01/followers",
      "subscriptionsUrl": "https://api.github.com/users/ali01/subscriptions",
      "organizationsUrl": "https://api.github.com/users/ali01/orgs",
      "reposUrl": "https://api.github.com/users/ali01/repos",
      "receivedEventsUrl": "https://api.github.com/users/ali01/received_events",
      "type": "User",
      "contributions": 4
    },
    {
      "login": "lgierth",
      "id": 19248,
      "avatarUrl": "https://avatars.githubusercontent.com/u/19248?v=3",
      "gravatarId": "",
      "url": "https://api.github.com/users/lgierth",
      "htmlUrl": "https://github.com/lgierth",
      "followersUrl": "https://api.github.com/users/lgierth/followers",
      "subscriptionsUrl": "https://api.github.com/users/lgierth/subscriptions",
      "organizationsUrl": "https://api.github.com/users/lgierth/orgs",
      "reposUrl": "https://api.github.com/users/lgierth/repos",
      "receivedEventsUrl": "https://api.github.com/users/lgierth/received_events",
      "type": "User",
      "contributions": 4
    },
    {
      "login": "flyingzumwalt",
      "id": 138930,
      "avatarUrl": "https://avatars.githubusercontent.com/u/138930?v=3",
      "gravatarId": "",
      "url": "https://api.github.com/users/flyingzumwalt",
      "htmlUrl": "https://github.com/flyingzumwalt",
      "followersUrl": "https://api.github.com/users/flyingzumwalt/followers",
      "subscriptionsUrl": "https://api.github.com/users/flyingzumwalt/subscriptions",
      "organizationsUrl": "https://api.github.com/users/flyingzumwalt/orgs",
      "reposUrl": "https://api.github.com/users/flyingzumwalt/repos",
      "receivedEventsUrl": "https://api.github.com/users/flyingzumwalt/received_events",
      "type": "User",
      "contributions": 2
    },
    {
      "login": "jmithmstr",
      "id": 20073694,
      "avatarUrl": "https://avatars.githubusercontent.com/u/20073694?v=3",
      "gravatarId": "",
      "url": "https://api.github.com/users/jmithmstr",
      "htmlUrl": "https://github.com/jmithmstr",
      "followersUrl": "https://api.github.com/users/jmithmstr/followers",
      "subscriptionsUrl": "https://api.github.com/users/jmithmstr/subscriptions",
      "organizationsUrl": "https://api.github.com/users/jmithmstr/orgs",
      "reposUrl": "https://api.github.com/users/jmithmstr/repos",
      "receivedEventsUrl": "https://api.github.com/users/jmithmstr/received_events",
      "type": "User",
      "contributions": 2
    },
    {
      "login": "slothbag",
      "id": 811824,
      "avatarUrl": "https://avatars.githubusercontent.com/u/811824?v=3",
      "gravatarId": "",
      "url": "https://api.github.com/users/slothbag",
      "htmlUrl": "https://github.com/slothbag",
      "followersUrl": "https://api.github.com/users/slothbag/followers",
      "subscriptionsUrl": "https://api.github.com/users/slothbag/subscriptions",
      "organizationsUrl": "https://api.github.com/users/slothbag/orgs",
      "reposUrl": "https://api.github.com/users/slothbag/repos",
      "receivedEventsUrl": "https://api.github.com/users/slothbag/received_events",
      "type": "User",
      "contributions": 2
    },
    {
      "login": "cleichner",
      "id": 769380,
      "avatarUrl": "https://avatars.githubusercontent.com/u/769380?v=3",
      "gravatarId": "",
      "url": "https://api.github.com/users/cleichner",
      "htmlUrl": "https://github.com/cleichner",
      "followersUrl": "https://api.github.com/users/cleichner/followers",
      "subscriptionsUrl": "https://api.github.com/users/cleichner/subscriptions",
      "organizationsUrl": "https://api.github.com/users/cleichner/orgs",
      "reposUrl": "https://api.github.com/users/cleichner/repos",
      "receivedEventsUrl": "https://api.github.com/users/cleichner/received_events",
      "type": "User",
      "contributions": 1
    },
    {
      "login": "dali99",
      "id": 990767,
      "avatarUrl": "https://avatars.githubusercontent.com/u/990767?v=3",
      "gravatarId": "",
      "url": "https://api.github.com/users/dali99",
      "htmlUrl": "https://github.com/dali99",
      "followersUrl": "https://api.github.com/users/dali99/followers",
      "subscriptionsUrl": "https://api.github.com/users/dali99/subscriptions",
      "organizationsUrl": "https://api.github.com/users/dali99/orgs",
      "reposUrl": "https://api.github.com/users/dali99/repos",
      "receivedEventsUrl": "https://api.github.com/users/dali99/received_events",
      "type": "User",
      "contributions": 1
    },
    {
      "login": "shurcooL",
      "id": 1924134,
      "avatarUrl": "https://avatars.githubusercontent.com/u/1924134?v=3",
      "gravatarId": "",
      "url": "https://api.github.com/users/shurcooL",
      "htmlUrl": "https://github.com/shurcooL",
      "followersUrl": "https://api.github.com/users/shurcooL/followers",
      "subscriptionsUrl": "https://api.github.com/users/shurcooL/subscriptions",
      "organizationsUrl": "https://api.github.com/users/shurcooL/orgs",
      "reposUrl": "https://api.github.com/users/shurcooL/repos",
      "receivedEventsUrl": "https://api.github.com/users/shurcooL/received_events",
      "type": "User",
      "contributions": 1
    },
    {
      "login": "heavenlyhash",
      "id": 627638,
      "avatarUrl": "https://avatars.githubusercontent.com/u/627638?v=3",
      "gravatarId": "",
      "url": "https://api.github.com/users/heavenlyhash",
      "htmlUrl": "https://github.com/heavenlyhash",
      "followersUrl": "https://api.github.com/users/heavenlyhash/followers",
      "subscriptionsUrl": "https://api.github.com/users/heavenlyhash/subscriptions",
      "organizationsUrl": "https://api.github.com/users/heavenlyhash/orgs",
      "reposUrl": "https://api.github.com/users/heavenlyhash/repos",
      "receivedEventsUrl": "https://api.github.com/users/heavenlyhash/received_events",
      "type": "User",
      "contributions": 1
    },
    {
      "login": "jerodsanto",
      "id": 8212,
      "avatarUrl": "https://avatars.githubusercontent.com/u/8212?v=3",
      "gravatarId": "",
      "url": "https://api.github.com/users/jerodsanto",
      "htmlUrl": "https://github.com/jerodsanto",
      "followersUrl": "https://api.github.com/users/jerodsanto/followers",
      "subscriptionsUrl": "https://api.github.com/users/jerodsanto/subscriptions",
      "organizationsUrl": "https://api.github.com/users/jerodsanto/orgs",
      "reposUrl": "https://api.github.com/users/jerodsanto/repos",
      "receivedEventsUrl": "https://api.github.com/users/jerodsanto/received_events",
      "type": "User",
      "contributions": 1
    },
    {
      "login": "jonjonsonjr",
      "id": 2533984,
      "avatarUrl": "https://avatars.githubusercontent.com/u/2533984?v=3",
      "gravatarId": "",
      "url": "https://api.github.com/users/jonjonsonjr",
      "htmlUrl": "https://github.com/jonjonsonjr",
      "followersUrl": "https://api.github.com/users/jonjonsonjr/followers",
      "subscriptionsUrl": "https://api.github.com/users/jonjonsonjr/subscriptions",
      "organizationsUrl": "https://api.github.com/users/jonjonsonjr/orgs",
      "reposUrl": "https://api.github.com/users/jonjonsonjr/repos",
      "receivedEventsUrl": "https://api.github.com/users/jonjonsonjr/received_events",
      "type": "User",
      "contributions": 1
    },
    {
      "login": "waffle-iron",
      "id": 6912981,
      "avatarUrl": "https://avatars.githubusercontent.com/u/6912981?v=3",
      "gravatarId": "",
      "url": "https://api.github.com/users/waffle-iron",
      "htmlUrl": "https://github.com/waffle-iron",
      "followersUrl": "https://api.github.com/users/waffle-iron/followers",
      "subscriptionsUrl": "https://api.github.com/users/waffle-iron/subscriptions",
      "organizationsUrl": "https://api.github.com/users/waffle-iron/orgs",
      "reposUrl": "https://api.github.com/users/waffle-iron/repos",
      "receivedEventsUrl": "https://api.github.com/users/waffle-iron/received_events",
      "type": "User",
      "contributions": 1
    },
    {
      "login": "mekarpeles",
      "id": 978325,
      "avatarUrl": "https://avatars.githubusercontent.com/u/978325?v=3",
      "gravatarId": "",
      "url": "https://api.github.com/users/mekarpeles",
      "htmlUrl": "https://github.com/mekarpeles",
      "followersUrl": "https://api.github.com/users/mekarpeles/followers",
      "subscriptionsUrl": "https://api.github.com/users/mekarpeles/subscriptions",
      "organizationsUrl": "https://api.github.com/users/mekarpeles/orgs",
      "reposUrl": "https://api.github.com/users/mekarpeles/repos",
      "receivedEventsUrl": "https://api.github.com/users/mekarpeles/received_events",
      "type": "User",
      "contributions": 1
    },
    {
      "login": "mburns",
      "id": 5170,
      "avatarUrl": "https://avatars.githubusercontent.com/u/5170?v=3",
      "gravatarId": "",
      "url": "https://api.github.com/users/mburns",
      "htmlUrl": "https://github.com/mburns",
      "followersUrl": "https://api.github.com/users/mburns/followers",
      "subscriptionsUrl": "https://api.github.com/users/mburns/subscriptions",
      "organizationsUrl": "https://api.github.com/users/mburns/orgs",
      "reposUrl": "https://api.github.com/users/mburns/repos",
      "receivedEventsUrl": "https://api.github.com/users/mburns/received_events",
      "type": "User",
      "contributions": 1
    },
    {
      "login": "mortonfox",
      "id": 495892,
      "avatarUrl": "https://avatars.githubusercontent.com/u/495892?v=3",
      "gravatarId": "",
      "url": "https://api.github.com/users/mortonfox",
      "htmlUrl": "https://github.com/mortonfox",
      "followersUrl": "https://api.github.com/users/mortonfox/followers",
      "subscriptionsUrl": "https://api.github.com/users/mortonfox/subscriptions",
      "organizationsUrl": "https://api.github.com/users/mortonfox/orgs",
      "reposUrl": "https://api.github.com/users/mortonfox/repos",
      "receivedEventsUrl": "https://api.github.com/users/mortonfox/received_events",
      "type": "User",
      "contributions": 1
    },
    {
      "login": "doesntgolf",
      "id": 5479469,
      "avatarUrl": "https://avatars.githubusercontent.com/u/5479469?v=3",
      "gravatarId": "",
      "url": "https://api.github.com/users/doesntgolf",
      "htmlUrl": "https://github.com/doesntgolf",
      "followersUrl": "https://api.github.com/users/doesntgolf/followers",
      "subscriptionsUrl": "https://api.github.com/users/doesntgolf/subscriptions",
      "organizationsUrl": "https://api.github.com/users/doesntgolf/orgs",
      "reposUrl": "https://api.github.com/users/doesntgolf/repos",
      "receivedEventsUrl": "https://api.github.com/users/doesntgolf/received_events",
      "type": "User",
      "contributions": 1
    },
    {
      "login": "NomadeLampe",
      "id": 4312697,
      "avatarUrl": "https://avatars.githubusercontent.com/u/4312697?v=3",
      "gravatarId": "",
      "url": "https://api.github.com/users/NomadeLampe",
      "htmlUrl": "https://github.com/NomadeLampe",
      "followersUrl": "https://api.github.com/users/NomadeLampe/followers",
      "subscriptionsUrl": "https://api.github.com/users/NomadeLampe/subscriptions",
      "organizationsUrl": "https://api.github.com/users/NomadeLampe/orgs",
      "reposUrl": "https://api.github.com/users/NomadeLampe/repos",
      "receivedEventsUrl": "https://api.github.com/users/NomadeLampe/received_events",
      "type": "User",
      "contributions": 1
    },
    {
      "login": "pra85",
      "id": 829526,
      "avatarUrl": "https://avatars.githubusercontent.com/u/829526?v=3",
      "gravatarId": "",
      "url": "https://api.github.com/users/pra85",
      "htmlUrl": "https://github.com/pra85",
      "followersUrl": "https://api.github.com/users/pra85/followers",
      "subscriptionsUrl": "https://api.github.com/users/pra85/subscriptions",
      "organizationsUrl": "https://api.github.com/users/pra85/orgs",
      "reposUrl": "https://api.github.com/users/pra85/repos",
      "receivedEventsUrl": "https://api.github.com/users/pra85/received_events",
      "type": "User",
      "contributions": 1
    },
    {
      "login": "richardschneider",
      "id": 631061,
      "avatarUrl": "https://avatars.githubusercontent.com/u/631061?v=3",
      "gravatarId": "",
      "url": "https://api.github.com/users/richardschneider",
      "htmlUrl": "https://github.com/richardschneider",
      "followersUrl": "https://api.github.com/users/richardschneider/followers",
      "subscriptionsUrl": "https://api.github.com/users/richardschneider/subscriptions",
      "organizationsUrl": "https://api.github.com/users/richardschneider/orgs",
      "reposUrl": "https://api.github.com/users/richardschneider/repos",
      "receivedEventsUrl": "https://api.github.com/users/richardschneider/received_events",
      "type": "User",
      "contributions": 1
    },
    {
      "login": "rmorey",
      "id": 4590343,
      "avatarUrl": "https://avatars.githubusercontent.com/u/4590343?v=3",
      "gravatarId": "",
      "url": "https://api.github.com/users/rmorey",
      "htmlUrl": "https://github.com/rmorey",
      "followersUrl": "https://api.github.com/users/rmorey/followers",
      "subscriptionsUrl": "https://api.github.com/users/rmorey/subscriptions",
      "organizationsUrl": "https://api.github.com/users/rmorey/orgs",
      "reposUrl": "https://api.github.com/users/rmorey/repos",
      "receivedEventsUrl": "https://api.github.com/users/rmorey/received_events",
      "type": "User",
      "contributions": 1
    },
    {
      "login": "tcyrus",
      "id": 4201229,
      "avatarUrl": "https://avatars.githubusercontent.com/u/4201229?v=3",
      "gravatarId": "",
      "url": "https://api.github.com/users/tcyrus",
      "htmlUrl": "https://github.com/tcyrus",
      "followersUrl": "https://api.github.com/users/tcyrus/followers",
      "subscriptionsUrl": "https://api.github.com/users/tcyrus/subscriptions",
      "organizationsUrl": "https://api.github.com/users/tcyrus/orgs",
      "reposUrl": "https://api.github.com/users/tcyrus/repos",
      "receivedEventsUrl": "https://api.github.com/users/tcyrus/received_events",
      "type": "User",
      "contributions": 1
    },
    {
      "login": "wking",
      "id": 209920,
      "avatarUrl": "https://avatars.githubusercontent.com/u/209920?v=3",
      "gravatarId": "",
      "url": "https://api.github.com/users/wking",
      "htmlUrl": "https://github.com/wking",
      "followersUrl": "https://api.github.com/users/wking/followers",
      "subscriptionsUrl": "https://api.github.com/users/wking/subscriptions",
      "organizationsUrl": "https://api.github.com/users/wking/orgs",
      "reposUrl": "https://api.github.com/users/wking/repos",
      "receivedEventsUrl": "https://api.github.com/users/wking/received_events",
      "type": "User",
      "contributions": 1
    },
    {
      "login": "yuvallanger",
      "id": 536362,
      "avatarUrl": "https://avatars.githubusercontent.com/u/536362?v=3",
      "gravatarId": "",
      "url": "https://api.github.com/users/yuvallanger",
      "htmlUrl": "https://github.com/yuvallanger",
      "followersUrl": "https://api.github.com/users/yuvallanger/followers",
      "subscriptionsUrl": "https://api.github.com/users/yuvallanger/subscriptions",
      "organizationsUrl": "https://api.github.com/users/yuvallanger/orgs",
      "reposUrl": "https://api.github.com/users/yuvallanger/repos",
      "receivedEventsUrl": "https://api.github.com/users/yuvallanger/received_events",
      "type": "User",
      "contributions": 1
    },
    {
      "login": "digital-dreamer",
      "id": 4333826,
      "avatarUrl": "https://avatars.githubusercontent.com/u/4333826?v=3",
      "gravatarId": "",
      "url": "https://api.github.com/users/digital-dreamer",
      "htmlUrl": "https://github.com/digital-dreamer",
      "followersUrl": "https://api.github.com/users/digital-dreamer/followers",
      "subscriptionsUrl": "https://api.github.com/users/digital-dreamer/subscriptions",
      "organizationsUrl": "https://api.github.com/users/digital-dreamer/orgs",
      "reposUrl": "https://api.github.com/users/digital-dreamer/repos",
      "receivedEventsUrl": "https://api.github.com/users/digital-dreamer/received_events",
      "type": "User",
      "contributions": 1
    },
    {
      "login": "wbnns",
      "id": 1130872,
      "avatarUrl": "https://avatars.githubusercontent.com/u/1130872?v=3",
      "gravatarId": "",
      "url": "https://api.github.com/users/wbnns",
      "htmlUrl": "https://github.com/wbnns",
      "followersUrl": "https://api.github.com/users/wbnns/followers",
      "subscriptionsUrl": "https://api.github.com/users/wbnns/subscriptions",
      "organizationsUrl": "https://api.github.com/users/wbnns/orgs",
      "reposUrl": "https://api.github.com/users/wbnns/repos",
      "receivedEventsUrl": "https://api.github.com/users/wbnns/received_events",
      "type": "User",
      "contributions": 1
    }
  ],
  "url": "/repos/ipfs/ipfs/contributors"
}